botapi/__init__.py
botapi/exceptions.py
botapi/field.py
botapi/model.py
botapi/serialize.py
botapi/type_cast.py
botapi/types.py
botapi/utils.py
botapi-1.2.1.dist-info/LICENSE.txt
botapi-1.2.1.dist-info/METADATA
botapi-1.2.1.dist-info/WHEEL
botapi-1.2.1.dist-info/top_level.txt
botapi-1.2.1.dist-info/RECORD
